moonstreamdbv3/__init__.py
moonstreamdbv3/blockchain.py
moonstreamdbv3/db.py
moonstreamdbv3/models.py
moonstreamdbv3/models_indexes.py
moonstreamdbv3/version.py
moonstreamdbv3/alembic/__init__.py
moonstreamdbv3/alembic/env.py
moonstreamdbv3/alembic/versions/090c247f8618_seer_raw_index.py
moonstreamdbv3/alembic/versions/1d53afc1eff4_add_b3.py
moonstreamdbv3/alembic/versions/211646463e9f_immutable_zkevm_with_it_s_sepolia_.py
moonstreamdbv3/alembic/versions/2e90b758090c_bytea_address_in_labels.py
moonstreamdbv3/alembic/versions/994e614b5500_tables_initial_generation.py
moonstreamdbv3/alembic/versions/9ca39b11e12a_game7_orbit_and_mantle_blockchain_models.py
moonstreamdbv3/alembic/versions/__init__.py
moonstreamdbv3/alembic/versions/bebe640146b6_add_raw_transactions.py
moonstreamdbv3/alembic/versions/c79044e047fe_declarative_indexes.py
moonstreamdbv3/alembic/versions/d2ceff33be47_tx_call_and_event_unique_indexes.py
moonstreamdbv3/alembic/versions/d816689b786a_add_game7_mainnet_labels.py
moonstreamdbv3/alembic/versions/dae735afc98f_remove_not_null_constrains.py
moonstreamdbv3/alembic/versions/db9559f9566c_add_game7_testnet.py
moonstreamdbv3/alembic/versions/e6d3c285e7cc_add_ronin_chain.py
moonstreamdbv3/alembic/versions/e9e1b43f49e1_amoy_blast_and_apex_blockchains.py
moonstreamdbv3/alembic/versions/e9f640a2b45b_arbitrum_one_blockchain.py
moonstreamdbv3/alembic_indexes/__init__.py
moonstreamdbv3/alembic_indexes/env.py
moonstreamdbv3/alembic_indexes/versions/0ea24314c181_init_v3_index.py
moonstreamdbv3/alembic_indexes/versions/25b339f55f8f_add_b3.py
moonstreamdbv3/alembic_indexes/versions/27086791044c_add_topic_3.py
moonstreamdbv3/alembic_indexes/versions/48d2562504d1_add_indexed_at_logs_and_transactions.py
moonstreamdbv3/alembic_indexes/versions/5ce23893771f_add_deployed_by_column.py
moonstreamdbv3/alembic_indexes/versions/6807bdf6f417_add_deploy_block.py
moonstreamdbv3/alembic_indexes/versions/82ff1541f4b4_add_contracts_tables.py
moonstreamdb_v3-0.1.6.dist-info/METADATA
moonstreamdb_v3-0.1.6.dist-info/WHEEL
moonstreamdb_v3-0.1.6.dist-info/top_level.txt
moonstreamdb_v3-0.1.6.dist-info/RECORD
